[
    {
        "title": "Tercerespai",
        "description": "Club de cinema independent a Barcelona",
        "imageUrl": "/tercerespai.png",
        "link": "https://tercerespai.org"
    },
    {
        "title": "Project Two",
        "description": "A brief description of Project Two.",
        "imageUrl": "https://picsum.photos/id/200/600/400",
        "link": "#"
    },
    {
        "title": "Project Three",
        "description": "A brief description of Project One.",
        "imageUrl": "https://picsum.photos/id/700/600/400",
        "link": "#"
    },
    {
        "title": "Project Four",
        "description": "A brief description of Project Two.",
        "imageUrl": "https://picsum.photos/id/800/600/400",
        "link": "#"
    },
    {
        "title": "Project Five",
        "description": "A brief description of Project One.",
        "imageUrl": "https://picsum.photos/id/900/600/400",
        "link": "#"
    },
    {
        "title": "Project Six",
        "description": "A brief description of Project Two.",
        "imageUrl": "https://picsum.photos/id/1000/600/400",
        "link": "#"
    }
]